{
    "services":[
        {
            "id": 1,
            "name": "haircut",
            "duration": 80
        },
        {
            "id": 2,
            "name": "nails",
            "duration": 120
        },
        {
            "id": 3,
            "name": "spa",
            "duration": 200
        },
        {
            "id": 4,
            "name": "makeup",
            "duration": 30
        }
    ],
    "employees":[
        {
            "id": 1,
            "name": "Alina Zagitova",
            "rate": 5.0,
            "companyId": 1,
            "services": [2]
        },
        {
            "id": 2,
            "name": "Valentin Strikalo",
            "rate": 3.0,
            "companyId": 1,
            "services": [1,4]
        },
        {
            "id": 3,
            "name": "Evgeniya Medvedeva",
            "rate": 3.0,
            "companyId": 1,
            "services": [2]
        },
        {
            "id": 4,
            "name": "Angenila Jolie",
            "rate": 5.0,
            "companyId": 2,
            "services": [1,4]
        },
        {
            "id": 5,
            "name": "Samantha Jones",
            "rate": 5.0,
            "companyId": 2,
            "services": [2]
        },
        {
            "id": 6,
            "name": "Anonymous",
            "rate": 0.0,
            "companyId": 3,
            "services": [1]
        }
    ],
    "companies": [
        {
            "id": 1,
            "name": "G.Bar",
            "website": "https://gbar.com.ua/",
            "locations": ["Vulytsya Zarichna, 1в, Kyiv, Ukraine"],
            "services": [ 1, 2, 3, 4 ],
            "workingHours": "0 10-18 * * Mon-Fri *" 
        },
        {
            "id": 2,
            "name": "The girls",
            "website": "https://thegirls.com.ua/",
            "locations": ["Horyva street, 41, Kyiv, Ukraine", "Heroiv Stalingrada avenue, 12ж, Kyiv, Ukraine"],
            "services": [1,2,4],
            "workingHours": "0 8-20 * * Mon-Sun *" 
        },
        {
            "id": 3,
            "name": "Beauty lab MV",
            "locations": ["Yelyzavety Chavdar St, 13, Kyiv, Ukraine"],
            "services": [1],
            "workingHours": "0 10-18 * * Mon-Sun *" 
        }
    ]
}